adrs/__init__.py
adrs/alpha.py
adrs/installer.py
adrs/json.py
adrs/portfolio.py
adrs/types.py
adrs/utils.py
adrs/data/__init__.py
adrs/data/dataloader.py
adrs/data/datamap.py
adrs/data/event.py
adrs/data/processor.py
adrs/data/types.py
adrs/performance/__init__.py
adrs/performance/evaluator.py
adrs/performance/metric/__init__.py
adrs/performance/metric/drawdown.py
adrs/performance/metric/metric.py
adrs/performance/metric/ratio.py
adrs/performance/metric/trade.py
adrs/report/__init__.py
adrs/report/alpha.py
adrs/report/portfolio.py
adrs/search/__init__.py
adrs/search/grid.py
adrs/search/random.py
adrs/search/search.py
adrs/tests/__init__.py
adrs/tests/sensitivity.py
adrs/wheels/aion-0.1.0-cp314-cp314-manylinux_2_17_aarch64.manylinux2014_aarch64.whl
adrs/wheels/cybotrade-2.0.14-cp314-cp314-manylinux_2_17_aarch64.manylinux2014_aarch64.whl
adrs/wheels/flow-1.0.9-cp314-cp314-manylinux_2_17_aarch64.manylinux2014_aarch64.whl
adrs-1.0.4.dist-info/METADATA
adrs-1.0.4.dist-info/WHEEL
adrs-1.0.4.dist-info/licenses/LICENSE
adrs-1.0.4.dist-info/RECORD
