Metadata-Version: 2.4
Name: adrs
Version: 1.0.4
Summary: Alpha development research system.
Project-URL: Homepage, https://github.com/balaenaquant/adrs.git
Author-email: Marcus Lee <marcuslee@balaenaquant.com>
License:                     GNU AFFERO GENERAL PUBLIC LICENSE
License-File: LICENSE
Classifier: Programming Language :: Python
Classifier: Programming Language :: Python :: 3
Classifier: Programming Language :: Python :: 3 :: Only
Classifier: Programming Language :: Python :: 3.12
Classifier: Programming Language :: Python :: 3.13
Classifier: Programming Language :: Python :: 3.14
Requires-Python: >=3.12
Requires-Dist: colorlog>=6.10.1
Requires-Dist: cybotrade-datasource>=0.1.9
Requires-Dist: numpy>=2.3.1
Requires-Dist: pandas>=2.3.0
Requires-Dist: pandera>=0.26.0
Requires-Dist: polars>=1.35.0
Requires-Dist: pyarrow>=22.0.0
Requires-Dist: pydantic>=2.11.7
